odoo10_addon_l10n_ch_credit_control_payment_slip_report-10.0.1.0.0.99.dev5-py3.8-nspkg.pth
odoo/addons/l10n_ch_credit_control_payment_slip_report/README.rst
odoo/addons/l10n_ch_credit_control_payment_slip_report/__init__.py
odoo/addons/l10n_ch_credit_control_payment_slip_report/__manifest__.py
odoo/addons/l10n_ch_credit_control_payment_slip_report/i18n/fr.po
odoo/addons/l10n_ch_credit_control_payment_slip_report/i18n/it.po
odoo/addons/l10n_ch_credit_control_payment_slip_report/i18n/l10n_ch_credit_control_payment_slip_report.pot
odoo/addons/l10n_ch_credit_control_payment_slip_report/models/__init__.py
odoo/addons/l10n_ch_credit_control_payment_slip_report/models/credit_control_communication_report.py
odoo/addons/l10n_ch_credit_control_payment_slip_report/models/credit_control_printer.py
odoo/addons/l10n_ch_credit_control_payment_slip_report/models/payment_slip.py
odoo/addons/l10n_ch_credit_control_payment_slip_report/readme/CONTRIBUTORS.rst
odoo/addons/l10n_ch_credit_control_payment_slip_report/readme/DESCRIPTION.rst
odoo/addons/l10n_ch_credit_control_payment_slip_report/security/ir.model.access.csv
odoo/addons/l10n_ch_credit_control_payment_slip_report/static/description/icon.png
odoo/addons/l10n_ch_credit_control_payment_slip_report/static/description/index.html
odoo/addons/l10n_ch_credit_control_payment_slip_report/tests/__init__.py
odoo/addons/l10n_ch_credit_control_payment_slip_report/tests/test_payment_slip_report.py
odoo/addons/l10n_ch_credit_control_payment_slip_report/views/credit_control_printer_view.xml
odoo/addons/l10n_ch_credit_control_payment_slip_report/views/report.xml
odoo10_addon_l10n_ch_credit_control_payment_slip_report-10.0.1.0.0.99.dev5.dist-info/METADATA
odoo10_addon_l10n_ch_credit_control_payment_slip_report-10.0.1.0.0.99.dev5.dist-info/WHEEL
odoo10_addon_l10n_ch_credit_control_payment_slip_report-10.0.1.0.0.99.dev5.dist-info/namespace_packages.txt
odoo10_addon_l10n_ch_credit_control_payment_slip_report-10.0.1.0.0.99.dev5.dist-info/top_level.txt
odoo10_addon_l10n_ch_credit_control_payment_slip_report-10.0.1.0.0.99.dev5.dist-info/RECORD
