Metadata-Version: 2.1
Name: odoo10-addon-l10n-ch-credit-control-payment-slip-report
Version: 10.0.1.0.0.99.dev5
Summary: Print ISR slip related to credit control
Home-page: https://github.com/OCA/l10n-switzerland
Author: Camptocamp,Odoo Community Association (OCA)
Author-email: support@odoo-community.org
License: AGPL-3
Platform: UNKNOWN
Classifier: Programming Language :: Python
Classifier: Framework :: Odoo
Classifier: Framework :: Odoo :: 10.0
Classifier: License :: OSI Approved :: GNU Affero General Public License v3
Requires-Python: ~=2.7
Requires-Dist: odoo10-addon-account-credit-control
Requires-Dist: odoo10-addon-account-credit-control-dunning-fees
Requires-Dist: odoo10-addon-l10n-ch-payment-slip
Requires-Dist: odoo <10.1dev,>=10.0
